examples/example.py
test/test_measure.py
tira_measure/__init__.py
tira_measure/libmeasureapi.so
tira_measure/py.typed
tira_measure-0.0.11.dist-info/METADATA
tira_measure-0.0.11.dist-info/WHEEL
tira_measure-0.0.11.dist-info/top_level.txt
tira_measure-0.0.11.dist-info/RECORD
